PikhtovSerLib/__init__.py
PikhtovSerLib/constants.py
PikhtovSerLib/create_ser.py
PikhtovSerLib/json_serealazer.py
PikhtovSerLib/main.py
PikhtovSerLib/my_serelizator.py
PikhtovSerLib/xml_serealazer.py
PikhtovSerLib-0.1.2.dist-info/METADATA
PikhtovSerLib-0.1.2.dist-info/WHEEL
PikhtovSerLib-0.1.2.dist-info/top_level.txt
PikhtovSerLib-0.1.2.dist-info/RECORD
